d8s_pdfs/__init__.py
d8s_pdfs/pdfs.py
d8s_pdfs/pdfs_temp_utils.py
tests/__init__.py
tests/test_pdfs.py
tests/data/sample.pdf
tests/data/sample.txt
d8s_pdfs-0.6.0.dist-info/COPYING
d8s_pdfs-0.6.0.dist-info/COPYING.LESSER
d8s_pdfs-0.6.0.dist-info/METADATA
d8s_pdfs-0.6.0.dist-info/WHEEL
d8s_pdfs-0.6.0.dist-info/top_level.txt
d8s_pdfs-0.6.0.dist-info/zip-safe
d8s_pdfs-0.6.0.dist-info/RECORD
